hydreservoir/__init__.py
hydreservoir/columns_constant.py
hydreservoir/regulation/dataset.py
hydreservoir/regulation/regulation.py
hydreservoir/utils.py
hydreservoir/water_balance/dataset.py
hydreservoir/water_balance/hydraulic_calculations.py
hydreservoir/water_balance/hydraulic_work.py
hydreservoir/water_balance/v2/hydraulic_component/__init__.py
hydreservoir/water_balance/v2/hydraulic_component/adjustable.py
hydreservoir/water_balance/v2/hydraulic_component/base_box_culvert.py
hydreservoir/water_balance/v2/hydraulic_component/base_circular_culvert.py
hydreservoir/water_balance/v2/hydraulic_component/base_culvert.py
hydreservoir/water_balance/v2/hydraulic_component/base_free_spillway.py
hydreservoir/water_balance/v2/hydraulic_component/base_gated_spillway.py
hydreservoir/water_balance/v2/hydraulic_component/base_spillway.py
hydreservoir/water_balance/v2/hydraulic_component/core.py
hydreservoir/water_balance/v2/hydraulic_component/culvert/box.py
hydreservoir/water_balance/v2/hydraulic_component/culvert/circular.py
hydreservoir/water_balance/v2/hydraulic_component/culvert/circular_v2.py
hydreservoir/water_balance/v2/hydraulic_component/need_free_spillway.py
hydreservoir/water_balance/v2/hydraulic_component/passive.py
hydreservoir/water_balance/v2/hydraulic_component/round.py
hydreservoir/water_balance/v2/hydraulic_component/simple/pump.py
hydreservoir/water_balance/v2/hydraulic_component/simple/unknown.py
hydreservoir/water_balance/v2/hydraulic_component/simple_discharge.py
hydreservoir/water_balance/v2/hydraulic_component/spillway/free_spillway.py
hydreservoir/water_balance/v2/hydraulic_component/spillway/gated_spillway.py
hydreservoir/water_balance/v2/hydraulic_component/straight.py
hydreservoir/water_balance/v2/wb.py
hydreservoir/water_balance/water_balance.py
hydreservoir-1.1.0.dist-info/LICENSE
hydreservoir-1.1.0.dist-info/METADATA
hydreservoir-1.1.0.dist-info/WHEEL
hydreservoir-1.1.0.dist-info/RECORD
