Metadata-Version: 2.1
Name: hydreservoir
Version: 1.1.0
Summary: HydReservoir is a Python library for hydrological calculations related to reservoirs.
License: MIT
Author: Duy Nguyen
Author-email: duynguyen02.dev@gmail.com
Requires-Python: >=3.10,<4.0
Classifier: License :: OSI Approved :: MIT License
Classifier: Programming Language :: Python :: 3
Classifier: Programming Language :: Python :: 3.10
Classifier: Programming Language :: Python :: 3.11
Classifier: Programming Language :: Python :: 3.12
Classifier: Programming Language :: Python :: 3.13
Requires-Dist: hydutils (>=1.0.0,<2.0.0)
Requires-Dist: pandas (>=2.2.3,<3.0.0)
